Workbook

Sheet T. S2 microarray results
A1: Public ID | B1: Gene | I1: Gene description | J1: sch9/wt | K1: ras2/wt | L1: tor1/wt
A2: YAL001C | B2: TFC3 | I2: Largest of six subunits of the RNA polymerase III transcription initiation factor complex (TFIIIC), part of the TauB domain of TFIIIC that binds DNA at the BoxB promoter sites of tRNA and similar genes, cooperates with Tfc6p in DNA binding | J2: -0.3306111 | K2: -0.591746 | L2: -0.4050345
A3: YAL002W | B3: VPS8 | I3: Membrane-associated hydrophilic protein that interacts with the small GTPase, Vps21p, to facilitate soluble vacuolar protein localization, required for localization and trafficking of the CPY sorting receptor, contains a RING finger motif | J3: 0.04337617 | K3: -0.1137375 | L3: 0.006602213
A4: YAL003W | B4: EFB1 | I4: Translation elongation factor 1 beta, stimulates nucleotide exchange to regenerate EF-1 alpha-GTP for the next elongation cycle, part of the EF-1 complex, which facilitates binding of aminoacyl-tRNA to the ribosomal A site | J4: 0.4574232 | K4: 0.3051455 | L4: 0.4256898
A5: YAL005C | B5: SSA2 | C5: SSA1 | I5: ATP binding protein involved in protein folding and vacuolar import of proteins, member of heat shock protein 70 (HSP70) family, associated with the chaperonin-containing T-complex, present in the cytoplasm, vacuolar membrane and cell wall ATPase involved in protein folding and nuclear localization signal (NLS)-directed nuclear transport, member of heat shock protein 70 (HSP70) family, forms a chaperone complex with Ydj1p, localized to the nucleus, cytoplasm, and cell wall | J5: 0.4046161 | K5: 0.5262972 | L5: 0.5405332
A6: YAL007C | B6: ERP2 | I6: Protein that forms a heterotrimeric complex with Erp1p, Emp24p, and Erv25p, member, along with Emp24p and Erv25p, of the p24 family involved in ER to Golgi transport and localized to COPII-coated vesicles | J6: 0.261135 | K6: 0.6099756 | L6: 0.4683093
A7: YAL008W | B7: FUN14 | I7: Mitochondrial protein of unknown function | J7: 0.2856357 | K7: 0.7606662 | L7: 0.4454354
A8: YAL009W | B8: SPO7 | I8: Integral nuclearER membrane protein of unknown function, required for normal nuclear envelope morphology and sporulation | J8: 0.2816513 | K8: 0.3294875 | L8: 0.3487153
A9: YAL010C | B9: MDM10 | I9: Subunit of the mitochondrial sorting and assembly machinery (SAM complex), has a role in assembly of the TOM complex, which mediates protein import through the outer membrane, required for normal mitochondrial morphology and inheritance | J9: -0.1904569 | K9: -0.1016729 | L9: -0.000173538
A10: YAL011W | B10: SWC3 | I10: Protein of unknown function, component of the Swr1p complex that incorporates Htz1p into chromatin, required for formation of nuclear-associated array of smooth endoplasmic reticulum known as karmellae | J10: -0.2772261 | K10: -0.5650292 | L10: -0.4100454
A11: YAL012W | B11: CYS3 | I11: Cystathionine gamma-lyase, catalyzes one of the two reactions involved in the transsulfuration pathway that yields cysteine from homocysteine with the intermediary formation of cystathionine, | J11: 0.3629012 | K11: 2.289331 | L11: 1.463729
A12: YAL013W | B12: DEP1 | I12: Transcriptional modulator involved in the regulation of structural genes involved in phospholipid biosynthesis, also participates in regulation of metabolically unrelated genes as well as maintenance of mating efficiency and sporulation | J12: 0.2752761 | K12: 0.004748148 | L12: 0.2537479
A13: YAL014C | B13: SYN8 | I13: Endosomal SNARE related to mammalian syntaxin 8 | J13: 0.4895598 | K13: 0.6373698 | L13: 0.4405245
A14: YAL015C | B14: NTG1 | I14: DNA N-glycosylase and apurinicapyrimidinic (AP) lyase involved in base excision repair, localizes to the nucleus and mitochondrion | J14: 0.3314654 | K14: -0.3319789 | L14: 0.05383845
A15: YAL016C-B | B15: --- | I15: Identified by fungal homology and RT-PCR | J15: -0.2296202 | K15: -0.25955 | L15: -0.1683807
A16: YAL016W | B16: TPD3 | I16: Regulatory subunit A of the heterotrimeric protein phosphatase 2A, which also contains regulatory subunit Cdc55p and either catalytic subunit Pph21p or Pph22p, required for cell morphogenesis and for transcription by RNA polymerase III | J16: -0.1345241 | K16: -0.1092769 | L16: -0.006014937
A17: YAL017W | B17: PSK1 | I17: One of two (see also PSK2) PAS domain containing ST protein kinases, coordinately regulates protein synthesis and carbohydrate metabolism and storage in response to a unknown metabolite that reflects nutritional status | J17: -0.3032663 | K17: -0.729649 | L17: -0.4077454
... A61: YAL062W | B61: GDH3 | I61: NADP(+)-dependent glutamate dehydrogenase, synthesizes glutamate from ammonia and alpha-ketoglutarate, rate of alpha-ketoglutarate utilization differs from Gdh1p, expression regulated by nitrogen and carbon sources | J61: 0.1478735 | K61: 0.3257182 | L61: -0.02448432
A62: YAL063C | B62: FLO5 | C62: FLO9 | D62: FLO1 | I62: Lectin-like protein involved in flocculation, cell wall protein that binds to mannose chains on the surface of other cells, confers floc-forming ability that is chymotrypsin resistant but heat labile, similar to Flo1p Lectin-like protein with similarity to Flo1p, thought to be expressed and involved in flocculation Lectin-like protein involved in flocculation, cell wall protein that binds to mannose chains on the surface of other cells, confers floc-forming ability that is chymotrypsin sensitive and heat resistant, similar to Flo5p | J62: -0.08677335 | K62: 0.474296 | L62: 0.1042248
A63: YAL063C-A | B63: --- | I63: Identified by expression profiling and mass spectrometry | J63: -0.2138284 | K63: 1.052111 | L63: 0.3248847
A64: YAL064C-A | B64: --- | I64: Hypothetical protein | J64: -0.1279343 | K64: 0.09968682 | L64: -0.03509193
A65: YAL064W | B65: --- | I65: Hypothetical protein | J65: -0.1943685 | K65: -0.1566463 | L65: -0.150287
A66: YAL064W-B | B66: --- | I66: Hypothetical protein | J66: -0.4461807 | K66: -0.1629928 | L66: -0.4600532
A67: YAL065C | B67: --- | I67: Hypothetical protein | J67: -0.6079561 | K67: -0.4641998 | L67: -0.4185536
A68: YAL067C | B68: SEO1 | I68: Putative permease, member of the allantoate transporter subfamily of the major facilitator superfamily, mutation confers resistance to ethionine sulfoxide | J68: -0.2041933 | K68: 1.521019 | L68: 0.5804801
A69: YAL067W-A | B69: --- | I69: Identified by gene-trapping, microarray-based expression analysis, and genome-wide homology searching Hypothetical protein Hypothetical protein Identified by gene-trapping, microarray-based expression analysis, and genome-wide homology searching | J69: 0.03219915 | K69: 0.4661268 | L69: 0.1737204
A70: YAL068C | B70: PAU4 | C70: PAU6 | D70: PAU1 | E70: PAU2 | F70: DAN3 | I70: Part of 23-member seripauperin multigene family encoded mainly in subtelomeric regions, active during alcoholic fermentation, regulated by anaerobiosis, negatively regulated by oxygen, repressed by heme Hypothetical protein Part of 23-member seripauperin multigene family encoded mainly in subtelomeric regions, active during alcoholic fermentation, regulated by anaerobiosis, negatively regulated by oxygen, repressed by heme Hypothetical protein Part of 23-member seripauperin multigene family encoded mainly in subtelomeric regions, active during alcoholic fermentation, regulated by anaerobiosis, negatively regulated by oxygen, repressed by heme Hypothetical protein Hypothetical protein Hypothetical protein Hypothetical protein Part of 23-member seripauperin multigene family encoded mainly in subtelomeric regions, active during alcoholic fermentation, regulated by anaerobiosis, negatively regulated by oxygen, repressed by heme Hypothetical protein Cell wall mannoprotein with similarity to Tir1p, Tir2p, Tir3p, and Tir4p, expressed under anaerobic conditions, completely repressed during aerobic growth Hypothetical protein Hypothetical protein identified by homology. See FEBS Letters [2000] 487:31-36. | J70: -0.3969555 | K70: 0.2500766 | L70: 0.3103923
A71: YAR002C-A | B71: ERP1 | I71: Protein that forms a heterotrimeric complex with Erp2p, Emp24p, and Erv25p, member, along with Emp24p and Erv25p, of the p24 family involved in ER to Golgi transport and localized to COPII-coated vesicles | J71: -0.004772137 | K71: 0.3688506 | L71: 0.199006
A72: YAR002W | B72: NUP60 | I72: Subunit of the nuclear pore complex (NPC), functions to anchor Nup2p to the NPC in a dynamic process that is controlled by the nucleoplasmic concentration of Gsp1p-GTP, potential Cdc28p substrate | J72: -0.2923209 | K72: -0.0904122 | L72: -0.1713251
A73: YAR003W | B73: SWD1 | I73: Subunit of the COMPASS (Set1C) complex, which methylates Rad6p ubiquitinated histone H3 on lysine 4 and is required in transcriptional silencing near telomeres, WD40 beta propeller superfamily member with similarity to mammalian Rbbp7 | J73: -0.07463264 | K73: -0.005272889 | L73: -0.147948
A74: YAR007C | B74: RFA1 | I74: Subunit of heterotrimeric Replication Factor A (RF-A), which is a highly conserved single-stranded DNA binding protein involved in DNA replication, repair, and recombination | J74: -0.6220847 | K74: -0.8557639 | L74: -0.555766
A75: YAR008W | B75: SEN34 | I75: Subunit of the tRNA splicing endonuclease, which is composed of Sen2p, Sen15p, Sen34p, and Sen54p, Sen34p contains the active site for tRNA 3 splice site cleavage and has similarity to Sen2p and to Archaeal tRNA splicing endonuclease | J75: 0.01630292 | K75: -0.501172 | L75: 0.3310486
A76: YAR009C | B76: --- | I76: TyB Gag-Pol protein, proteolytically processed to make the Gag, RT, PR, and IN proteins that are required for retrotransposition TyB Gag-Pol protein, proteolytically processed to make the Gag, RT, PR, and IN proteins that are required for retrotransposition TyB Gag-Pol protein, proteolytically processed to make the Gag, RT, PR, and IN proteins that are required for retrotransposition TyB Gag-Pol protein, proteolytically processed to make the Gag, RT, PR, and IN proteins that are required for retrotransposition TyB Gag-Pol protein, proteolytically processed to make the Gag, RT, PR, and IN proteins that are required for retrotransposition TyB Gag-Pol protein, proteolytically processed to make the Gag, RT, PR, and IN proteins that are required for retrotransposition TyB Gag-Pol protein, proteolytically processed to make the Gag, RT, PR, and IN proteins that are required for retrotransposition TyB Gag-Pol protein, proteolytically processed to make the Gag, RT, PR, and IN proteins that are required for retrotransposition TyB Gag-Pol protein, proteolytically processed to make the Gag, RT, PR, and IN proteins that are required for retrotransposition TyB Gag-Pol protein, proteolytically processed to make the Gag, RT, PR, and IN proteins that are required for retrotransposition TyB Gag-Pol protein, proteolytically processed to make the Gag, RT, PR, and IN proteins that are required for retrotransposition TyB Gag-Pol protein, proteolytically processed to make the Gag, RT, PR, and IN proteins that are required for retrotransposition TyB Gag-Pol protein, proteolytically processed to make the Gag, RT, PR, and IN proteins that are required for retrotransposition TyB Gag-Pol protein, proteolytically processed to make the Gag, RT, PR, and IN proteins that are required for retrotransposition TyB Gag-Pol protein, proteolytically processed to make the Gag, RT, PR, and IN proteins that are required for retrotransposition TyB Gag-Pol protein, proteolytically processed to make the Gag, RT, PR, and IN proteins that are required for retrotransposition TyB Gag-Pol protein, proteolytically processed to make the Gag, RT, PR, and IN proteins that are required for retrotransposition Ty ORF TyB Gag-Pol protein, proteolytically processed to make the Gag, RT, PR, and IN proteins that are required for retrotransposition TyB Gag-Pol protein, proteolytically processed to make the Gag, RT, PR, and IN proteins that are required for retrotransposition TyB Gag-Pol protein, proteolytically processed to make the Gag, RT, PR, and IN proteins that are required for retrotransposition TyB Gag-Pol protein, proteolytically processed to make the Gag, RT, PR, and IN proteins that are required for retrotransposition TyB Gag-Pol protein, proteolytically processed to make the Gag, RT, PR, and IN proteins that are required for retrotransposition TyB Gag-Pol protein, proteolytically processed to make the Gag, RT, PR, and IN proteins that are required for retrotransposition TyB Gag-Pol protein, proteolytically processed to make the Gag, RT, PR, and IN proteins that are required for retrotransposition TyB Gag-Pol protein, proteolytically processed to make the Gag, RT, PR, and IN proteins that are required for retrotransposition TyB Gag-Pol protein, proteolytically processed to make the Gag, RT, PR, and IN proteins that are required for retrotransposition TyB Gag-Pol protein, proteolytically processed to make the Gag, RT, PR, and IN proteins that are required for retrotransposition TyB Gag-Pol protein, proteolytically processed to make the Gag, RT, PR, and IN proteins that are required for retrotransposition TyB Gag-Pol protein, proteolytically processed to make the Gag, RT, PR, and IN proteins that are required for retrotransposition TyB Gag-Pol protein, proteolytically processed to make the Gag, RT, PR, and IN proteins that are required for retrotransposition TyB Gag-Pol protein, proteolytically processed to make the Gag, RT, PR, and IN proteins that are required for retrotransposition TyB Gag-Pol protein, proteolytically processed to make the Gag, RT, PR, and IN proteins that are required for retrotransposition TyB Gag-Pol protein, proteolytically processed to make the Gag, RT, PR, and IN proteins that are required for retrotransposition TyB Gag-Pol protein, proteolytically processed to make the Gag, RT, PR, and IN proteins that are required for retrotransposition TyB Gag-Pol protein, proteolytically processed to make the Gag, RT, PR, and IN proteins that are required for retrotransposition TyB Gag-Pol protein, proteolytically processed to make the Gag, RT, PR, and IN proteins that are required for retrotransposition TyB Gag-Pol protein, proteolytically processed to make the Gag, RT, PR, and IN proteins that are required for retrotransposition TyB Gag-Pol protein, proteolytically processed to make the Gag, RT, PR, and IN proteins that are required for retrotransposition TyB Gag-Pol protein, proteolytically processed to make the Gag, RT, PR, and IN proteins that are required for retrotransposition TyB Gag-Pol protein, proteolytically processed to make the Gag, RT, PR, and IN proteins that are required for retrotransposition | J76: -1.370308 | K76: -0.9859324 | L76: -0.6930766
A77: YAR010C | B77: --- | I77: TyB Gag-Pol protein, proteolytically processed to make the Gag, RT, PR, and IN proteins that are required for retrotransposition TyA Gag protein, the main structural constituent of virus-like particles (VLPs) TyB Gag-Pol protein, proteolytically processed to make the Gag, RT, PR, and IN proteins that are required for retrotransposition TyA Gag protein, the main structural constituent of virus-like particles (VLPs) TyA Gag protein, the main structural constituent of virus-like particles (VLPs) TyB Gag-Pol protein, proteolytically processed to make the Gag, RT, PR, and IN proteins that are required for retrotransposition TyB Gag-Pol protein, proteolytically processed to make the Gag, RT, PR, and IN proteins that are required for retrotransposition TyA Gag protein, the main structural constituent of virus-like particles (VLPs) TyB Gag-Pol protein, proteolytically processed to make the Gag, RT, PR, and IN proteins that are required for retrotransposition TyA Gag protein, the main structural constituent of virus-like particles (VLPs) TyB Gag-Pol protein, proteolytically processed to make the Gag, RT, PR, and IN proteins that are required for retrotransposition TyA Gag protein, the main structural constituent of virus-like particles (VLPs) TyB Gag-Pol protein, proteolytically processed to make the Gag, RT, PR, and IN proteins that are required for retrotransposition TyA Gag protein, the main structural constituent of virus-like particles (VLPs) TyB Gag-Pol protein, proteolytically processed to make the Gag, RT, PR, and IN proteins that are required for retrotransposition TyB Gag-Pol protein, proteolytically processed to make the Gag, RT, PR, and IN proteins that are required for retrotransposition TyA Gag protein, the main structural constituent of virus-like particles (VLPs) TyB Gag-Pol protein, proteolytically processed to make the Gag, RT, PR, and IN proteins that are required for retrotransposition TyA Gag protein, the main structural constituent of virus-like particles (VLPs) Identified by expression profiling and mass spectrometry TyB Gag-Pol protein, proteolytically processed to make the Gag, RT, PR, and IN proteins that are required for retrotransposition TyA Gag protein, the main structural constituent of virus-like particles (VLPs) TyA Gag protein, the main structural constituent of virus-like particles (VLPs) TyB Gag-Pol protein, proteolytically processed to make the Gag, RT, PR, and IN proteins that are required for retrotransposition TyA Gag protein, the main structural constituent of virus-like particles (VLPs) TyA Gag protein, the main structural constituent of virus-like particles (VLPs) TyB Gag-Pol protein, proteolytically processed to make the Gag, RT, PR, and IN proteins that are required for retrotransposition TyA Gag protein, the main structural constituent of virus-like particles (VLPs) TyB Gag-Pol protein, proteolytically processed to make the Gag, RT, PR, and IN proteins that are required for retrotransposition Ty ORF TyB Gag-Pol protein, proteolytically processed to make the Gag, RT, PR, and IN proteins that are required for retrotransposition TyB Gag-Pol protein, proteolytically processed to make the Gag, RT, PR, and IN proteins that are required for retrotransposition TyA Gag protein, the main structural constituent of virus-like particles (VLPs) TyB Gag-Pol protein, proteolytically processed to make the Gag, RT, PR, and IN proteins that are required for retrotransposition TyA Gag protein, the main structural constituent of virus-like particles (VLPs) TyA Gag protein, the main structural constituent of virus-like particles (VLPs) TyB Gag-Pol protein, proteolytically processed to make the Gag, RT, PR, and IN proteins that are required for retrotransposition TyA Gag protein, the main structural constituent of virus-like particles (VLPs) TyB Gag-Pol protein, proteolytically processed to make the Gag, RT, PR, and IN proteins that are required for retrotransposition TyA Gag protein, the main structural constituent of virus-like particles (VLPs) TyB Gag-Pol protein, proteolytically processed to make the Gag, RT, PR, and IN proteins that are required for retrotransposition TyB Gag-Pol protein, proteolytically processed to make the Gag, RT, PR, and IN proteins that are required for retrotransposition TyA Gag protein, the main structural constituent of virus-like particles (VLPs) TyA Gag protein, the main structural constituent of virus-like particles (VLPs) TyB Gag-Pol protein, proteolytically processed to make the Gag, RT, PR, and IN proteins that are required for retrotransposition TyA Gag protein, the main structural constituent of virus-like particles (VLPs) TyB Gag-Pol protein, proteolytically processed to make the Gag, RT, PR, and IN proteins that are required for retrotransposition TyA Gag protein, the main structural constituent of virus-like particles (VLPs) TyB Gag-Pol protein, proteolytically processed to make the Gag, RT, PR, and IN proteins that are required for retrotransposition TyB Gag-Pol protein, proteolytically processed to make the Gag, RT, PR, and IN proteins that are required for retrotransposition TyA Gag protein, the main structural constituent of virus-like particles (VLPs) TyB Gag-Pol protein, proteolytically processed to make the Gag, RT, PR, and IN proteins that are required for retrotransposition TyA Gag protein, the main structural constituent of virus-like particles (VLPs) TyB Gag-Pol protein, proteolytically processed to make the Gag, RT, PR, and IN proteins that are required for retrotransposition TyA Gag protein, the main structural constituent of virus-like particles (VLPs) TyA Gag protein, the main structural constituent of virus-like particles (VLPs) TyB Gag-Pol protein, proteolytically processed to make the Gag, RT, PR, and IN proteins that are required for retrotransposition TyA Gag protein, the main structural constituent of virus-like particles (VLPs) TyB Gag-Pol protein, proteolytically processed to make the Gag, RT, PR, and IN proteins that are required for retrotransposition | J77: -0.5123691 | K77: -0.6682571 | L77: -0.5717717
A78: YAR014C | B78: BUD14 | I78: Protein involved in bud-site selection, diploid mutants display a random budding pattern instead of the wild-type bipolar pattern | J78: -0.507132 | K78: -0.9840414 | L78: -0.4319503
A79: YAR015W | B79: ADE1 | I79: N-succinyl-5-aminoimidazole-4-carboxamide ribotide (SAICAR) synthetase, required for de novo purine nucleotide biosynthesis, red pigment accumulates in mutant cells deprived of adenine | J79: 0.2633153 | K79: -0.115271 | L79: 0.7528612
A80: YAR018C | B80: KIN3 | I80: Nonessential protein kinase with unknown cellular role | J80: -0.2154747 | K80: -0.07369933 | L80: 0.1284762
A81: YAR019C | B81: CDC15 | I81: Protein kinase of the Mitotic Exit Network that is localized to the spindle pole bodies at late anaphase, promotes mitotic exit by directly switching on the kinase activity of Dbf2p | J81: -0.01695682 | K81: 0.1482022 | L81: -0.06900086
A82: YAR020C | B82: PAU7 | I82: Part of 23-member seripauperin multigene family, active during alcoholic fermentation, regulated by anaerobiosis, inhibited by oxygen, repressed by heme | J82: -0.03812366 | K82: 0.4380359 | L82: 0.2873593
... A87: YAR031W | B87: PRM9 | I87: Pheromone-regulated protein with 3 predicted transmembrane segments and an FF sequence, a motif involved in COPII binding | J87: 0.05818872 | K87: -0.0438543 | L87: 0.03389733
A88: YAR033W | B88: MST27 | C88: MST28 | I88: Putative integral membrane protein, involved in vesicle formation, forms complex with Mst28p, member of DUP240 gene family, binds COPI and COPII vesicles Putative integral membrane protein, involved in vesicle formation, forms complex with Mst27p, member of DUP240 gene family, binds COPI and COPII vesicles | J88: 0.1487839 | K88: 0.2440458 | L88: 0.09794402
A89: YAR035C-A | B89: --- | I89: Identified by gene-trapping, microarray-based expression analysis, and genome-wide homology searching | J89: 0.08094512 | K89: -0.03587767 | L89: 0.0303263
A90: YAR035W | B90: YAT1 | I90: Outer mitochondrial carnitine acetyltransferase, minor ethanol-inducible enzyme involved in transport of activated acyl groups from the cytoplasm into the mitochondrial matrix | J90: -0.04964793 | K90: -0.04792621 | L90: -0.0292396
A91: YAR042W | B91: SWH1 | I91: Protein similar to mammalian oxysterol-binding protein, contains ankyrin repeats, localizes to the Golgi and the nucleus-vacuole junction | J91: 0.08274725 | K91: 0.04257803 | L91: 0.03103441
A92: YAR050W | B92: FLO9 | C92: FLO1 | I92: Lectin-like protein with similarity to Flo1p, thought to be expressed and involved in flocculation Lectin-like protein involved in flocculation, cell wall protein that binds to mannose chains on the surface of other cells, confers floc-forming ability that is chymotrypsin sensitive and heat resistant, similar to Flo5p | J92: 0.06700605 | K92: 1.032076 | L92: 0.2451478
A93: YAR064W | B93: --- | I93: Identified by gene-trapping, microarray-based expression analysis, and genome-wide homology searching Hypothetical protein | J93: -0.2843394 | K93: -0.1871519 | L93: -0.2187281
A94: YAR066W | B94: --- | I94: putative membrane protein Hypothetical protein | J94: 0.2367592 | K94: 0.1997311 | L94: 0.2826611
A95: YAR068W | B95: --- | I95: putative membrane protein | J95: -0.04614974 | K95: -1.005831 | L95: 0.2178891
A96: YAR071W | B96: PHO12 | C96: PHO11 | I96: One of three repressible acid phosphatases, a glycoprotein that is transported to the cell surface by the secretory pathway, nearly identical to Pho11p, upregulated by phosphate starvation One of three repressible acid phosphatases, a glycoprotein that is transported to the cell surface by the secretory pathway, induced by phosphate starvation and coordinately regulated by PHO4 and PHO2 | J96: 0.8062617 | K96: 1.189747 | L96: 0.898369
A97: YAR073W | B97: IMD2 | C97: IMD1 | I97: Inosine monophosphate dehydrogenase, catalyzes the first step of GMP biosynthesis, expression is induced by mycophenolic acid resulting in resistance to the drug, expression is repressed by nutrient limitation Nonfunctional protein with homology to IMP dehydrogenase, IMD1 is a probable pseudogene that is located close to the telomere and is not expressed at detectable levels Hypothetical protein | J97: -0.3353268 | K97: -0.0902467 | L97: 0.09813352
A98: YAR075W | B98: IMD3 | C98: IMD2 | D98: IMD1 | I98: Inosine monophosphate dehydrogenase, catalyzes the first step of GMP biosynthesis, member of a four-gene family in S. cerevisiae, constitutively expressed Inosine monophosphate dehydrogenase, catalyzes the first step of GMP biosynthesis, expression is induced by mycophenolic acid resulting in resistance to the drug, expression is repressed by nutrient limitation Nonfunctional protein with homology to IMP dehydrogenase, IMD1 is a probable pseudogene that is located close to the telomere and is not expressed at detectable levels Hypothetical protein | J98: 0.05475142 | K98: 0.2745452 | L98: 0.2422639
A99: YBL001C | B99: ECM15 | I99: Non-essential protein of unknown function, likely exists as tetramer, may be regulated by the binding of small-molecule ligands (possibly sulfate ions), may have a role in yeast cell-wall biogenesis | J99: 0.1270988 | K99: 0.1930974 | L99: 0.2553195
A100: YBL002W | B100: HTB2 | I100: One of two nearly identical (see HTB1) histone H2B subtypes required for chromatin assembly and chromosome function, Rad6p-Bre1p-Lge1p mediated ubiquitination regulates transcriptional activation, meiotic DSB formation and H3 methylation | J100: 0.3185578 | K100: 0.4891944 | L100: 0.4335159
A101: YBL003C | B101: HTA2 | I101: One of two nearly identical (see also HTA1) histone H2A subtypes, core histone required for chromatin assembly and chromosome function, DNA damage-dependent phosphorylation by Mec1p facilitates DNA repair, acetylated by Nat4p | J101: 0.2740178 | K101: -0.02364838 | L101: 0.2794472
A102: YBL004W | B102: UTP20 | I102: Possible snoRNA-binding protein, based on computational analysis of large-scale protein-protein interaction data | J102: -0.2449927 | K102: -1.024186 | L102: -0.3604881
A103: YBL005W | B103: PDR3 | I103: Transcriptional activator of the pleiotropic drug resistance network, regulates expression of ATP-binding cassette (ABC) transporters through binding to cis-acting sites known as PDREs (PDR responsive elements) | J103: -0.04437851 | K103: 0.2739893 | L103: -0.0649683
A104: YBL005W-A | B104: --- | I104: TyB Gag-Pol protein, proteolytically processed to make the Gag, RT, PR, and IN proteins that are required for retrotransposition TyA Gag protein, the main structural constituent of virus-like particles (VLPs) TyA Gag protein, the main structural constituent of virus-like particles (VLPs) TyB Gag-Pol protein, proteolytically processed to make the Gag, RT, PR, and IN proteins that are required for retrotransposition TyB Gag-Pol protein, proteolytically processed to make the Gag, RT, PR, and IN proteins that are required for retrotransposition TyB Gag-Pol protein, proteolytically processed to make the Gag, RT, PR, and IN proteins that are required for retrotransposition TyB Gag-Pol protein, proteolytically processed to make the Gag, RT, PR, and IN proteins that are required for retrotransposition Ty ORF TyA Gag protein, the main structural constituent of virus-like particles (VLPs) TyB Gag-Pol protein, proteolytically processed to make the Gag, RT, PR, and IN proteins that are required for retrotransposition TyB Gag-Pol protein, proteolytically processed to make the Gag, RT, PR, and IN proteins that are required for retrotransposition | J104: -1.157471 | K104: -1.123579 | L104: -1.357626
A105: YBL006C | B105: LDB7 | I105: Protein of unknown function, null mutant shows a reduced affinity for the alcian blue dye suggesting a decreased net negative charge of the cell surface | J105: 0.4286113 | K105: -0.1610484 | L105: 0.3475116
A106: YBL007C | B106: SLA1 | I106: Cytoskeletal protein binding protein required for assembly of the cortical actin cytoskeleton, contains 3 SH3 domains, interacts with proteins regulating actin dynamics and with proteins required for endocytosis | J106: 0.2078713 | K106: 0.05945351 | L106: 0.0582238
A107: YBL008W | B107: HIR1 | I107: Non-essential transcriptional corepressor involved in the cell cycle-regulated transcription of histone H2A, H2B, H3 and H4 genes, contributes to nucleosome formation, heterochromatic gene silencing, and formation of functional kinetochores | J107: -0.3571059 | K107: -0.1329076 | L107: -0.4860161
A108: YBL008W-A | B108: --- | I108: Identified by fungal homology and RT-PCR | J108: 0.000621491 | K108: -0.04259437 | L108: 0.04167685
A109: YBL009W | B109: --- | I109: haspin | J109: -0.3853162 | K109: -0.4776446 | L109: -0.3329169
A110: YBL010C | B110: --- | I110: Hypothetical protein | J110: -0.512832 | K110: -1.040842 | L110: -0.3977704
... A125: YBL026W | B125: LSM2 | I125: Component of small nuclear ribonucleoprotein complexes involved in RNA processing, splicing, and decay | J125: -0.301573 | K125: -0.5902251 | L125: -0.2581115
A126: YBL027W | B126: RPL19B | C126: RPL19A | I126: Protein component of the large (60S) ribosomal subunit, nearly identical to Rpl19Bp and has similarity to rat L19 ribosomal protein, rpl19a and rpl19b single null mutations result in slow growth, while the double null mutation is lethal Protein component of the large (60S) ribosomal subunit, nearly identical to Rpl19Bp and has similarity to rat L19 ribosomal protein, rpl19a and rpl19b single null mutations result in slow growth, while the double null mutation is lethal | J126: 0.2492527 | K126: -0.2229908 | L126: 0.2951675
A127: YBL028C | B127: --- | I127: Hypothetical protein | J127: -0.005009625 | K127: -0.3876271 | L127: 0.1343263
A128: YBL029C-A | B128: --- | I128: Protein of unknown function, green fluorescent protein (GFP)-fusion protein localizes to the cell periphery, has potential orthologs in Saccharomyces species and in Yarrowia lipolytica | J128: 0.2101076 | K128: 0.07335678 | L128: 0.3482588
A129: YBL029W | B129: --- | I129: Hypothetical protein | J129: 0.3798742 | K129: 0.812413 | L129: 0.3580027
A130: YBL030C | B130: PET9 | I130: Major ADPATP carrier of the mitochondrial inner membrane, exchanges cytosolic ADP for mitochondrially synthesized ATP, required for viability in many common lab strains carrying a mutation in the polymorphic SAL1 gene | J130: -0.1669739 | K130: -0.1195319 | L130: -0.2304135
A131: YBL031W | B131: SHE1 | I131: Cytoskeletal protein of unknown function, overexpression causes growth arrest | J131: -0.1129381 | K131: -0.2797944 | L131: -0.1037216
A132: YBL032W | B132: HEK2 | I132: RNA binding protein with similarity to hnRNP-K that localizes to the cytoplasm and to subtelomeric DNA, required for the proper localization of ASH1 mRNA, involved in the regulation of telomere position effect and telomere length | J132: -0.3250814 | K132: -0.2942336 | L132: -0.3971356
A133: YBL033C | B133: RIB1 | I133: GTP cyclohydrolase II, catalyzes the first step of the riboflavin biosynthesis pathway | J133: -0.1419052 | K133: -0.8264818 | L133: -0.3843979
A134: YBL034C | B134: STU1 | I134: Component of the mitotic spindle that binds to interpolar microtubules via its association with beta-tubulin (Tub2p), required for interpolar microtubules to provide an outward force on the spindle poles | J134: 0.251554 | K134: 0.4070418 | L134: 0.3980339
A135: YBL035C | B135: POL12 | I135: B subunit of DNA polymerase alpha-primase complex, required for initiation of DNA replication during mitotic and premeiotic DNA synthesis, also functions in telomere capping and length regulation | J135: 0.1025727 | K135: 0.4177826 | L135: 0.2823235
A136: YBL036C | B136: --- | I136: Single-domain racemase, possibly non-specific due to the lack of the second domain, which presumably determines specificity | J136: -0.4883333 | K136: -0.7474444 | L136: -0.3125967
A137: YBL037W | B137: APL3 | I137: Alpha-adaptin, large subunit of the clathrin associated protein complex (AP-2), involved in vesicle mediated transport | J137: -0.7325052 | K137: -1.132082 | L137: -0.9830961
A138: YBL038W | B138: MRPL16 | I138: Mitochondrial ribosomal protein of the large subunit | J138: -0.6366348 | K138: -1.170286 | L138: -0.4994732
... A169: YBL071W-A | B169: KTI11 | I169: Protein required, along with Dph1p, Dph2p, Jjj3p, and Dph5p, for synthesis of diphthamide, which is a modified histidine residue of translation elongation factor 2 (Eft1p or Eft2p), may act in a complex with Dph1p and Dph2p | J169: 0.02793485 | K169: -0.09801487 | L169: 0.007423868
A170: YBL072C | B170: RPS8B | C170: RPS8A | I170: Protein component of the small (40S) ribosomal subunit, identical to Rps8Bp and has similarity to rat S8 ribosomal protein Protein component of the small (40S) ribosomal subunit, identical to Rps8Ap and has similarity to rat S8 ribosomal protein | J170: 0.6291267 | K170: 0.2412712 | L170: 0.6452655
A171: YBL074C | B171: AAR2 | I171: Component of the U5 snRNP, required for splicing of U3 precursors, originally described as a splicing factor specifically required for splicing pre-mRNA of the MATa1 cistron | J171: -0.3054715 | K171: -0.7913107 | L171: -0.2852986
A172: YBL075C | B172: SSA3 | I172: ATPase involved in protein folding and the response to stress, plays a role in SRP-dependent cotranslational protein-membrane targeting and translocation, member of the heat shock protein 70 (HSP70) family, localized to the cytoplasm | J172: 1.042691 | K172: 1.301535 | L172: 0.9152016
A173: YBL076C | B173: ILS1 | I173: Cytoplasmic isoleucine-tRNA synthetase, target of the G1-specific inhibitor reveromycin A | J173: -0.08817047 | K173: -1.043396 | L173: -0.5028945
A174: YBL078C | B174: ATG8 | I174: Protein required for autophagy, modified by the serial action of Atg4p, Atg7p, and Atg3p, and conjugated at the C terminus with phosphatidylethanolamine, to become the form essential for generation of autophagosomes | J174: -0.2200996 | K174: -0.3031956 | L174: -0.04616867
A175: YBL079W | B175: NUP170 | I175: Abundant subunit of the nuclear pore complex (NPC), required for proper localization of specific nucleoporins within the NPC, involved in nuclear envelope permeability and in chromosome segregation, has similarity to Nup157p | J175: 0.02058402 | K175: -0.3382007 | L175: -0.1855902
A176: YBL080C | B176: PET112 | I176: Protein required for mitochondrial translation, mutation is functionally complemented by a Bacillus subtilis ortholog | J176: 0.03528831 | K176: -0.4114912 | L176: -0.1748042
A177: YBL081W | B177: --- | I177: Hypothetical protein | J177: -0.5576669 | K177: 0.4113801 | L177: -0.01497752
A178: YBL082C | B178: ALG3 | I178: Dolichol-P-Man dependent alpha(1-3) mannosyltransferase, involved in the synthesis of dolichol-linked oligosaccharide donor for N-linked glycosylation of proteins | J178: -0.2133049 | K178: 1.203813 | L178: 0.5063615
A179: YBL084C | B179: CDC27 | I179: Subunit of the Anaphase-Promoting ComplexCyclosome (APCC), which is a ubiquitin-protein ligase required for degradation of anaphase inhibitors, including mitotic cyclins, during the metaphaseanaphase transition | J179: 0.571488 | K179: -0.3220094 | L179: 0.08618824
A180: YBL085W | B180: BOI1 | I180: Protein implicated in polar growth, functionally redundant with Boi2p, interacts with bud-emergence protein Bem1p, contains an SH3 (src homology 3) domain and a PH (pleckstrin homology) domain | J180: 0.4223451 | K180: 0.1203721 | L180: 0.1565363
A181: YBL086C | B181: --- | I181: Protein of unknown function, green fluorescent protein (GFP)-fusion protein localizes to the cell periphery | J181: -0.4902853 | K181: -0.8463396 | L181: -0.044283
A182: YBL087C | B182: RPL23A | I182: Protein component of the large (60S) ribosomal subunit, identical to Rpl23Bp and has similarity to E. coli L14 and rat L23 ribosomal proteins | J182: 0.08714865 | K182: 0.1018777 | L182: 0.08168888
... A203: YBL107C | B203: --- | I203: Hypothetical protein | J203: -0.9267309 | K203: -1.325211 | L203: -0.6063035
A204: YBL108C-A | B204: PAU4 | C204: PAU6 | D204: PAU1 | E204: PAU5 | F204: PAU2 | G204: DAN3 | I204: Part of 23-member seripauperin multigene family encoded mainly in subtelomeric regions, active during alcoholic fermentation, regulated by anaerobiosis, negatively regulated by oxygen, repressed by heme Hypothetical protein Part of 23-member seripauperin multigene family encoded mainly in subtelomeric regions, active during alcoholic fermentation, regulated by anaerobiosis, negatively regulated by oxygen, repressed by heme Hypothetical protein Part of 23-member seripauperin multigene family encoded mainly in subtelomeric regions, active during alcoholic fermentation, regulated by anaerobiosis, negatively regulated by oxygen, repressed by heme Hypothetical protein Hypothetical protein Hypothetical protein Hypothetical protein Part of 23-member seripauperin multigene family encoded mainly in subtelomeric regions, active during alcoholic fermentation, regulated by anaerobiosis, negatively regulated by oxygen, repressed by heme Part of 23-member seripauperin multigene family encoded mainly in subtelomeric regions, active during alcoholic fermentation, regulated by anaerobiosis, negatively regulated by oxygen, repressed by heme Hypothetical protein Cell wall mannoprotein with similarity to Tir1p, Tir2p, Tir3p, and Tir4p, expressed under anaerobic conditions, completely repressed during aerobic growth Hypothetical protein Hypothetical protein identified by homology. See FEBS Letters [2000] 487:31-36. | J204: 0.1043186 | K204: 0.5449957 | L204: 0.4789608
A205: YBL111C | B205: YRF1-5 | C205: YRF1-4 | D205: YRF1-7 | E205: YRF1-6 | F205: YRF1-3 | G205: YRF1-2 | H205: YRF1-1 | I205: Hypothetical protein Helicase encoded by the Y element of subtelomeric regions, highly expressed in the mutants lacking the telomerase component TLC1, potentially phosphorylated by Cdc28p Helicase encoded by the Y element of subtelomeric regions, highly expressed in the mutants lacking the telomerase component TLC1, potentially phosphorylated by Cdc28p Hypothetical protein Hypothetical protein similar to other subtelomerically-encoded proteins Hypothetical protein subtelomerically-encoded DNA helicase Helicase encoded by the Y element of subtelomeric regions, highly expressed in the mutants lacking the telomerase component TLC1, potentially phosphorylated by Cdc28p Hypothetical protein Helicase encoded by the Y element of subtelomeric regions, highly expressed in the mutants lacking the telomerase component TLC1, potentially phosphorylated by Cdc28p Hypothetical protein Hypothetical protein Hypothetical protein Hypothetical protein Hypothetical protein Hypothetical protein Protein of unknown function, potential Cdc28p substrate Helicase encoded by the Y element of subtelomeric regions, highly expressed in the mutants lacking the telomerase component TLC1, potentially phosphorylated by Cdc28p Hypothetical protein Hypothetical protein Hypothetical protein Helicase encoded by the Y element of subtelomeric regions, highly expressed in the mutants lacking the telomerase component TLC1, potentially phosphorylated by Cdc28p Hypothetical protein Hypothetical protein Hypothetical protein Hypothetical protein Hypothetical protein Helicase encoded by the Y element of subtelomeric regions, highly expressed in the mutants lacking the telomerase component TLC1, potentially phosphorylated by Cdc28p Hypothetical protein Hypothetical protein | J205: -0.2157551 | K205: -0.6549044 | L205: -0.5175223
A206: YBL112C | B206: YRF1-5 | C206: YRF1-4 | D206: YRF1-7 | E206: YRF1-6 | F206: YRF1-3 | G206: YRF1-2 | H206: YRF1-1 | I206: Hypothetical protein Helicase encoded by the Y element of subtelomeric regions, highly expressed in the mutants lacking the telomerase component TLC1, potentially phosphorylated by Cdc28p Helicase encoded by the Y element of subtelomeric regions, highly expressed in the mutants lacking the telomerase component TLC1, potentially phosphorylated by Cdc28p subtelomerically-encoded DNA helicase Helicase encoded by the Y element of subtelomeric regions, highly expressed in the mutants lacking the telomerase component TLC1, potentially phosphorylated by Cdc28p Hypothetical protein Helicase encoded by the Y element of subtelomeric regions, highly expressed in the mutants lacking the telomerase component TLC1, potentially phosphorylated by Cdc28p Hypothetical protein Hypothetical protein Hypothetical protein Hypothetical protein Hypothetical protein Helicase encoded by the Y element of subtelomeric regions, highly expressed in the mutants lacking the telomerase component TLC1, potentially phosphorylated by Cdc28p Helicase encoded by the Y element of subtelomeric regions, highly expressed in the mutants lacking the telomerase component TLC1, potentially phosphorylated by Cdc28p Hypothetical protein Helicase encoded by the Y element of subtelomeric regions, highly expressed in the mutants lacking the telomerase component TLC1, potentially phosphorylated by Cdc28p Hypothetical protein Hypothetical protein | J206: -0.1494245 | K206: -0.8919645 | L206: -0.3474858
A207: YBL113C | B207: YRF1-5 | C207: YRF1-4 | D207: YRF1-7 | E207: YRF1-6 | F207: YRF1-3 | G207: YRF1-2 | H207: YRF1-1 | I207: Hypothetical protein Helicase encoded by the Y element of subtelomeric regions, highly expressed in the mutants lacking the telomerase component TLC1, potentially phosphorylated by Cdc28p Helicase encoded by the Y element of subtelomeric regions, highly expressed in the mutants lacking the telomerase component TLC1, potentially phosphorylated by Cdc28p subtelomerically-encoded DNA helicase Helicase encoded by the Y element of subtelomeric regions, highly expressed in the mutants lacking the telomerase component TLC1, potentially phosphorylated by Cdc28p Hypothetical protein Helicase encoded by the Y element of subtelomeric regions, highly expressed in the mutants lacking the telomerase component TLC1, potentially phosphorylated by Cdc28p Hypothetical protein Hypothetical protein Hypothetical protein Hypothetical protein Hypothetical protein Hypothetical protein Protein of unknown function, potential Cdc28p substrate Helicase encoded by the Y element of subtelomeric regions, highly expressed in the mutants lacking the telomerase component TLC1, potentially phosphorylated by Cdc28p Hypothetical protein Helicase encoded by the Y element of subtelomeric regions, highly expressed in the mutants lacking the telomerase component TLC1, potentially phosphorylated by Cdc28p Hypothetical protein Helicase encoded by the Y element of subtelomeric regions, highly expressed in the mutants lacking the telomerase component TLC1, potentially phosphorylated by Cdc28p Hypothetical protein Hypothetical protein Hypothetical protein | J207: -0.1228656 | K207: -0.3459086 | L207: -0.171288
A208: YBR001C | B208: NTH2 | I208: Neutral trehalase, degrades trehalose, required for thermotolerance and may mediate resistance to other cellular stresses | J208: -0.02213151 | K208: 0.2905676 | L208: 0.005331898
A209: YBR002C | B209: RER2 | I209: Cis-prenyltransferase involved in dolichol synthesis, participates in endoplasmic reticulum (ER) protein sorting | J209: -0.2561941 | K209: -0.5892993 | L209: -0.3651473
A210: YBR003W | B210: COQ1 | I210: Hexaprenyl pyrophosphate synthetase, catalyzes the first step in ubiquinone (coenzyme Q) biosynthesis | J210: -0.4987813 | K210: -0.06425822 | L210: -0.4951573
A211: YBR004C | B211: GPI18 | I211: Functional ortholog of human PIG-V, which is a mannosyltransferase that transfers the second mannose in glycosylphosphatidylinositol biosynthesis, the authentic, non-tagged protein was localized to mitochondria | J211: 0.3878242 | K211: 0.1999278 | L211: 0.2326004
...

Sheet Count
A1: Gene1 | B1: Gene2 | C1: Gene3 | D1: Gene4 | E1: Gene5 | F1: Gene6 | G1: Gene7 | M1: COUNT :
A2: TFC3 | M2: A | N2: B | O2: C | P2: D | Q2: E | R2: F | S2: G | T2: H
A3: VPS8 | M3: =COUNTA(A$2:A$5668) -> 5667 | N3: =COUNTA(B$2:B$5668) -> 131 | O3: =COUNTA(C$2:C$5668) -> 29 | P3: =COUNTA(D$2:D$5668) -> 21 | Q3: =COUNTA(E$2:E$5668) -> 17 | R3: =COUNTA(F$2:F$5668) -> 10 | S3: =COUNTA(G$2:G$5668) -> 5 | T3: =COUNTA(H$2:H$5668) -> 0
A4: EFB1
A5: SSA2 | B5: SSA1
A6: ERP2 | K6: #Cadidate | L6: Genes: | P6: #Known | Q6: Longivity | R6: Genes:
A7: FUN14 | K7: YGL007W | L7: =COUNTIF($A$2:$G$5668,K7) -> 0 | P7: AGP1 | Q7: =COUNTIF($A$2:$G$5668,P7) -> 1
A8: SPO7 | K8: UBP6 | L8: =COUNTIF($A$2:$G$5668,K8) -> 1 | P8: ATP2 | Q8: =COUNTIF($A$2:$G$5668,P8) -> 1
A9: MDM10 | K9: HFI1 | L9: =COUNTIF($A$2:$G$5668,K9) -> 1 | P9: BCY1 | Q9: =COUNTIF($A$2:$G$5668,P9) -> 1
A10: SWC3 | K10: HST4 | L10: =COUNTIF($A$2:$G$5668,K10) -> 1 | P10: BRE5 | Q10: =COUNTIF($A$2:$G$5668,P10) -> 1
A11: CYS3 | K11: AKR1 | L11: =COUNTIF($A$2:$G$5668,K11) -> 1 | P11: CCS1 | Q11: =COUNTIF($A$2:$G$5668,P11) -> 1
A12: DEP1 | K12: ALF1 | L12: =COUNTIF($A$2:$G$5668,K12) -> 1 | P12: CDC25 | Q12: =COUNTIF($A$2:$G$5668,P12) -> 1
A13: SYN8 | K13: VPS30 | L13: =COUNTIF($A$2:$G$5668,K13) -> 1 | P13: CDC6 | Q13: =COUNTIF($A$2:$G$5668,P13) -> 1
A14: NTG1 | K14: SEC22 | L14: =COUNTIF($A$2:$G$5668,K14) -> 1 | P14: CHL1 | Q14: =COUNTIF($A$2:$G$5668,P14) -> 1
A15: --- | K15: PUT3 | L15: =COUNTIF($A$2:$G$5668,K15) -> 1 | P15: CLN3 | Q15: =COUNTIF($A$2:$G$5668,P15) -> 1
A16: TPD3 | K16: SRO9 | L16: =COUNTIF($A$2:$G$5668,K16) -> 1 | P16: CSR2 | Q16: =COUNTIF($A$2:$G$5668,P16) -> 1
A17: PSK1 | K17: GCN3 | L17: =COUNTIF($A$2:$G$5668,K17) -> 1 | P17: CTT1 | Q17: =COUNTIF($A$2:$G$5668,P17) -> 1
A18: --- | K18: HCS1 | L18: =COUNTIF($A$2:$G$5668,K18) -> 1 | P18: CYR1 | Q18: =COUNTIF($A$2:$G$5668,P18) -> 1
... A61: GDH3 | K61: NPT1 | L61: =COUNTIF($A$2:$G$5668,K61) -> 1 | P61: RPD3 | Q61: =COUNTIF($A$2:$G$5668,P61) -> 1
A62: FLO5 | B62: FLO9 | C62: FLO1 | K62: FUN26 | L62: =COUNTIF($A$2:$G$5668,K62) -> 1 | P62: RPL10 | Q62: =COUNTIF($A$2:$G$5668,P62) -> 1
A63: --- | K63: PEX28 | L63: =COUNTIF($A$2:$G$5668,K63) -> 1 | P63: RPL31A | Q63: =COUNTIF($A$2:$G$5668,P63) -> 2
A64: --- | K64: YNL241C | L64: =COUNTIF($A$2:$G$5668,K64) -> 0 | P64: RPL6B | Q64: =COUNTIF($A$2:$G$5668,P64) -> 1
A65: --- | K65: DOA4 | L65: =COUNTIF($A$2:$G$5668,K65) -> 1 | P65: RPO41 | Q65: =COUNTIF($A$2:$G$5668,P65) -> 1
A66: --- | K66: YJL171C | L66: =COUNTIF($A$2:$G$5668,K66) -> 0 | P66: RPS18A | Q66: =COUNTIF($A$2:$G$5668,P66) -> 2
A67: --- | K67: STC2 | L67: =COUNTIF($A$2:$G$5668,K67) -> 0 | P67: RPS18B | Q67: =COUNTIF($A$2:$G$5668,P67) -> 2
A68: SEO1 | K68: AHC1 | L68: =COUNTIF($A$2:$G$5668,K68) -> 1 | P68: RPS6B | Q68: =COUNTIF($A$2:$G$5668,P68) -> 1
A69: --- | K69: YNL266W | L69: =COUNTIF($A$2:$G$5668,K69) -> 0 | P69: RTG3 | Q69: =COUNTIF($A$2:$G$5668,P69) -> 1
A70: PAU4 | B70: PAU6 | C70: PAU1 | D70: PAU2 | E70: DAN3 | K70: RRN10 | L70: =COUNTIF($A$2:$G$5668,K70) -> 1 | P70: SCH9 | Q70: =COUNTIF($A$2:$G$5668,P70) -> 1
A71: ERP1 | K71: DCS1 | L71: =COUNTIF($A$2:$G$5668,K71) -> 1 | P71: SCP1 | Q71: =COUNTIF($A$2:$G$5668,P71) -> 1
A72: NUP60 | K72: ATS1 | L72: =COUNTIF($A$2:$G$5668,K72) -> 1 | P72: SGS1 | Q72: =COUNTIF($A$2:$G$5668,P72) -> 1
A73: SWD1 | K73: RNP1 | L73: =COUNTIF($A$2:$G$5668,K73) -> 1 | P73: SIP2 | Q73: =COUNTIF($A$2:$G$5668,P73) -> 1
A74: RFA1 | K74: GCN2 | L74: =COUNTIF($A$2:$G$5668,K74) -> 1 | P74: sir2 | Q74: =COUNTIF($A$2:$G$5668,P74) -> 1
A75: SEN34 | K75: MCT1 | L75: =COUNTIF($A$2:$G$5668,K75) -> 1 | P75: sir3 | Q75: =COUNTIF($A$2:$G$5668,P75) -> 1
A76: --- | K76: URE2 | L76: =COUNTIF($A$2:$G$5668,K76) -> 1 | P76: sir4 | Q76: =COUNTIF($A$2:$G$5668,P76) -> 1
A77: --- | K77: YET1 | L77: =COUNTIF($A$2:$G$5668,K77) -> 0 | P77: SNF1 | Q77: =COUNTIF($A$2:$G$5668,P77) -> 1
A78: BUD14 | K78: PEX17 | L78: =COUNTIF($A$2:$G$5668,K78) -> 1 | P78: SNF4 | Q78: =COUNTIF($A$2:$G$5668,P78) -> 1
A79: ADE1 | K79: RAD6 | L79: =COUNTIF($A$2:$G$5668,K79) -> 1 | P79: Sod1 | Q79: =COUNTIF($A$2:$G$5668,P79) -> 1
A80: KIN3 | K80: NPR1 | L80: =COUNTIF($A$2:$G$5668,K80) -> 1 | P80: Sod2 | Q80: =COUNTIF($A$2:$G$5668,P80) -> 1
A81: CDC15 | K81: YOR091W | L81: =COUNTIF($A$2:$G$5668,K81) -> 0 | P81: SSD1 | Q81: =COUNTIF($A$2:$G$5668,P81) -> 1
A82: PAU7 | K82: BUD16 | L82: =COUNTIF($A$2:$G$5668,K82) -> 1 | P82: TLC1 | Q82: =COUNTIF($A$2:$G$5668,P82) -> 0
... A87: PRM9 | K87: YGR242W | L87: =COUNTIF($A$2:$G$5668,K87) -> 0 | P87: UTH1 | Q87: =COUNTIF($A$2:$G$5668,P87) -> 1
A88: MST27 | B88: MST28 | K88: UPC2 | L88: =COUNTIF($A$2:$G$5668,K88) -> 1 | P88: YBR238C | Q88: =COUNTIF($A$2:$G$5668,P88) -> 0
A89: --- | K89: BNI4 | L89: =COUNTIF($A$2:$G$5668,K89) -> 1 | P89: YBR255W | Q89: =COUNTIF($A$2:$G$5668,P89) -> 0
A90: YAT1 | K90: EDE1 | L90: =COUNTIF($A$2:$G$5668,K90) -> 1 | P90: YKU70 | Q90: =COUNTIF($A$2:$G$5668,P90) -> 1
A91: SWH1 | K91: YDR433W | L91: =COUNTIF($A$2:$G$5668,K91) -> 0 | P91: YKU80 | Q91: =COUNTIF($A$2:$G$5668,P91) -> 1
A92: FLO9 | B92: FLO1 | K92: FMO | L92: =COUNTIF($A$2:$G$5668,K92) -> 0 | P92: ZDS1 | Q92: =COUNTIF($A$2:$G$5668,P92) -> 1
A93: --- | K93: YPL062W | L93: =COUNTIF($A$2:$G$5668,K93) -> 0
A94: --- | K94: YPL077C | L94: =COUNTIF($A$2:$G$5668,K94) -> 0
A95: --- | K95: YJL169W | L95: =COUNTIF($A$2:$G$5668,K95) -> 0
A96: PHO12 | B96: PHO11 | K96: YOR240W | L96: =COUNTIF($A$2:$G$5668,K96) -> 0
A97: IMD2 | B97: IMD1 | K97: RCY1 | L97: =COUNTIF($A$2:$G$5668,K97) -> 1
A98: IMD3 | B98: IMD2 | C98: IMD1 | K98: YGR228W | L98: =COUNTIF($A$2:$G$5668,K98) -> 0
A99: ECM15 | K99: MRS4 | L99: =COUNTIF($A$2:$G$5668,K99) -> 1
A100: HTB2 | K100: TOM6 | L100: =COUNTIF($A$2:$G$5668,K100) -> 1
A101: HTA2 | K101: MMS2 | L101: =COUNTIF($A$2:$G$5668,K101) -> 1
A102: UTP20 | K102: YDR317W | L102: =COUNTIF($A$2:$G$5668,K102) -> 0
A103: PDR3 | K103: VPS20 | L103: =COUNTIF($A$2:$G$5668,K103) -> 1
A104: --- | K104: WTM2 | L104: =COUNTIF($A$2:$G$5668,K104) -> 1
A105: LDB7 | K105: ARG82 | L105: =COUNTIF($A$2:$G$5668,K105) -> 1
A106: SLA1 | K106: ECM25 | L106: =COUNTIF($A$2:$G$5668,K106) -> 1
A107: HIR1 | K107: YBL009W | L107: =COUNTIF($A$2:$G$5668,K107) -> 0
A108: --- | K108: YJL184W | L108: =COUNTIF($A$2:$G$5668,K108) -> 0
A109: --- | K109: YOR251C | L109: =COUNTIF($A$2:$G$5668,K109) -> 0
A110: --- | K110: YOR214C | L110: =COUNTIF($A$2:$G$5668,K110) -> 0
... A125: LSM2 | K125: MLH1 | L125: =COUNTIF($A$2:$G$5668,K125) -> 1
A126: RPL19B | B126: RPL19A | K126: DSE3 | L126: =COUNTIF($A$2:$G$5668,K126) -> 1
A127: --- | K127: RPD3 | L127: =COUNTIF($A$2:$G$5668,K127) -> 1
A128: ---
A129: ---
A130: PET9
A131: SHE1
A132: HEK2
A133: RIB1
A134: STU1
A135: POL12
A136: ---
A137: APL3
A138: MRPL16
A139: URA7
... A169: KTI11
A170: RPS8B | B170: RPS8A
A171: AAR2
A172: SSA3
A173: ILS1
A174: ATG8
A175: NUP170
A176: PET112
A177: ---
A178: ALG3
A179: CDC27
A180: BOI1
A181: ---
A182: RPL23A
... A203: ---
A204: PAU4 | B204: PAU6 | C204: PAU1 | D204: PAU5 | E204: PAU2 | F204: DAN3
A205: YRF1-5 | B205: YRF1-4 | C205: YRF1-7 | D205: YRF1-6 | E205: YRF1-3 | F205: YRF1-2 | G205: YRF1-1
A206: YRF1-5 | B206: YRF1-4 | C206: YRF1-7 | D206: YRF1-6 | E206: YRF1-3 | F206: YRF1-2 | G206: YRF1-1
A207: YRF1-5 | B207: YRF1-4 | C207: YRF1-7 | D207: YRF1-6 | E207: YRF1-3 | F207: YRF1-2 | G207: YRF1-1
A208: NTH2
A209: RER2
...

Sheet Check
A1: #Candidate Genes | E1: #Known Longivity Genes
A2: {=_xlfn._xlws.FILTER(Count!K7:K127,Count!L7:L127 > 0)} -> UBP6 | E2: {=_xlfn._xlws.FILTER(Count!P7:P92,Count!Q7:Q92 > 0)} -> AGP1
A3: HFI1 | E3: ATP2
A4: HST4 | E4: BCY1
A5: AKR1 | E5: BRE5
A6: ALF1 | E6: CCS1
A7: VPS30 | E7: CDC25
A8: SEC22 | E8: CDC6
A9: PUT3 | E9: CHL1
A10: SRO9 | E10: CLN3
A11: GCN3 | E11: CSR2
A12: HCS1 | E12: CTT1
A13: CDC10 | E13: CYR1
A14: RGD1 | E14: DNA2
... A84: DUR1,2 | E84: ZDS1
A85: ELP2
A86: MLH1
A87: DSE3
A88: RPD3

Sheet CLeaned Data
A1: Public ID | B1: Genes | C1: Types | D1: Name | E1: Known | F1: sch9/wt | G1: ras2/wt | H1: tor1/wt
A2: {=INDEX('T. S2 microarray results'!A:A, MATCH(TRUE, ('T. S2 microarray results'!B:B=B2) + ('T. S2 microarray results'!C:C=B2) + ('T. S2 microarray results'!D:D=B2) + ('T. S2 microarray results'!E:E=B2) + ('T. S2 microarray results'!F:F=B2) + ('T. S2 microarray results'!G:G=B2) + ('T. S2 microarray results'!H:H=B2) > 0, 0))} -> YFR010W | B2: UBP6 | C2: Candidate Gene | D2: =CONCATENATE(IF(C2="Known Longivity Gene","*",""),A2,"/",B2) -> YFR010W/UBP6 | E2: =IF(C2="Known Longivity Gene",1,0) -> 0 | F2: {=INDEX('T. S2 microarray results'!J:J, MATCH(TRUE, ('T. S2 microarray results'!B:B=B2) + ('T. S2 microarray results'!C:C=B2) + ('T. S2 microarray results'!D:D=B2) + ('T. S2 microarray results'!E:E=B2) + ('T. S2 microarray results'!F:F=B2) + ('T. S2 microarray results'!G:G=B2) + ('T. S2 microarray results'!H:H=B2) > 0, 0))} -> 0.1556491 | G2: {=INDEX('T. S2 microarray results'!K:K, MATCH(TRUE, ('T. S2 microarray results'!B:B=B2) + ('T. S2 microarray results'!C:C=B2) + ('T. S2 microarray results'!D:D=B2) + ('T. S2 microarray results'!E:E=B2) + ('T. S2 microarray results'!F:F=B2) + ('T. S2 microarray results'!G:G=B2) + ('T. S2 microarray results'!H:H=B2) > 0, 0))} -> -0.4880185 | H2: {=INDEX('T. S2 microarray results'!L:L, MATCH(TRUE, ('T. S2 microarray results'!B:B=B2) + ('T. S2 microarray results'!C:C=B2) + ('T. S2 microarray results'!D:D=B2) + ('T. S2 microarray results'!E:E=B2) + ('T. S2 microarray results'!F:F=B2) + ('T. S2 microarray results'!G:G=B2) + ('T. S2 microarray results'!H:H=B2) > 0, 0))} -> 0.07698462
A3: {=INDEX('T. S2 microarray results'!A:A, MATCH(TRUE, ('T. S2 microarray results'!B:B=B3) + ('T. S2 microarray results'!C:C=B3) + ('T. S2 microarray results'!D:D=B3) + ('T. S2 microarray results'!E:E=B3) + ('T. S2 microarray results'!F:F=B3) + ('T. S2 microarray results'!G:G=B3) + ('T. S2 microarray results'!H:H=B3) > 0, 0))} -> YPL254W | B3: HFI1 | C3: Candidate Gene | D3: =CONCATENATE(IF(C3="Known Longivity Gene","*",""),A3,"/",B3) -> YPL254W/HFI1 | E3: =IF(C3="Known Longivity Gene",1,0) -> 0 | F3: {=INDEX('T. S2 microarray results'!J:J, MATCH(TRUE, ('T. S2 microarray results'!B:B=B3) + ('T. S2 microarray results'!C:C=B3) + ('T. S2 microarray results'!D:D=B3) + ('T. S2 microarray results'!E:E=B3) + ('T. S2 microarray results'!F:F=B3) + ('T. S2 microarray results'!G:G=B3) + ('T. S2 microarray results'!H:H=B3) > 0, 0))} -> 0.05905491 | G3: {=INDEX('T. S2 microarray results'!K:K, MATCH(TRUE, ('T. S2 microarray results'!B:B=B3) + ('T. S2 microarray results'!C:C=B3) + ('T. S2 microarray results'!D:D=B3) + ('T. S2 microarray results'!E:E=B3) + ('T. S2 microarray results'!F:F=B3) + ('T. S2 microarray results'!G:G=B3) + ('T. S2 microarray results'!H:H=B3) > 0, 0))} -> 0.2101467 | H3: {=INDEX('T. S2 microarray results'!L:L, MATCH(TRUE, ('T. S2 microarray results'!B:B=B3) + ('T. S2 microarray results'!C:C=B3) + ('T. S2 microarray results'!D:D=B3) + ('T. S2 microarray results'!E:E=B3) + ('T. S2 microarray results'!F:F=B3) + ('T. S2 microarray results'!G:G=B3) + ('T. S2 microarray results'!H:H=B3) > 0, 0))} -> -0.1090477
A4: {=INDEX('T. S2 microarray results'!A:A, MATCH(TRUE, ('T. S2 microarray results'!B:B=B4) + ('T. S2 microarray results'!C:C=B4) + ('T. S2 microarray results'!D:D=B4) + ('T. S2 microarray results'!E:E=B4) + ('T. S2 microarray results'!F:F=B4) + ('T. S2 microarray results'!G:G=B4) + ('T. S2 microarray results'!H:H=B4) > 0, 0))} -> YDR191W | B4: HST4 | C4: Candidate Gene | D4: =CONCATENATE(IF(C4="Known Longivity Gene","*",""),A4,"/",B4) -> YDR191W/HST4 | E4: =IF(C4="Known Longivity Gene",1,0) -> 0 | F4: {=INDEX('T. S2 microarray results'!J:J, MATCH(TRUE, ('T. S2 microarray results'!B:B=B4) + ('T. S2 microarray results'!C:C=B4) + ('T. S2 microarray results'!D:D=B4) + ('T. S2 microarray results'!E:E=B4) + ('T. S2 microarray results'!F:F=B4) + ('T. S2 microarray results'!G:G=B4) + ('T. S2 microarray results'!H:H=B4) > 0, 0))} -> 0.5468464 | G4: {=INDEX('T. S2 microarray results'!K:K, MATCH(TRUE, ('T. S2 microarray results'!B:B=B4) + ('T. S2 microarray results'!C:C=B4) + ('T. S2 microarray results'!D:D=B4) + ('T. S2 microarray results'!E:E=B4) + ('T. S2 microarray results'!F:F=B4) + ('T. S2 microarray results'!G:G=B4) + ('T. S2 microarray results'!H:H=B4) > 0, 0))} -> 0.7314741 | H4: {=INDEX('T. S2 microarray results'!L:L, MATCH(TRUE, ('T. S2 microarray results'!B:B=B4) + ('T. S2 microarray results'!C:C=B4) + ('T. S2 microarray results'!D:D=B4) + ('T. S2 microarray results'!E:E=B4) + ('T. S2 microarray results'!F:F=B4) + ('T. S2 microarray results'!G:G=B4) + ('T. S2 microarray results'!H:H=B4) > 0, 0))} -> 0.3387958
A5: {=INDEX('T. S2 microarray results'!A:A, MATCH(TRUE, ('T. S2 microarray results'!B:B=B5) + ('T. S2 microarray results'!C:C=B5) + ('T. S2 microarray results'!D:D=B5) + ('T. S2 microarray results'!E:E=B5) + ('T. S2 microarray results'!F:F=B5) + ('T. S2 microarray results'!G:G=B5) + ('T. S2 microarray results'!H:H=B5) > 0, 0))} -> YDR264C | B5: AKR1 | C5: Candidate Gene | D5: =CONCATENATE(IF(C5="Known Longivity Gene","*",""),A5,"/",B5) -> YDR264C/AKR1 | E5: =IF(C5="Known Longivity Gene",1,0) -> 0 | F5: {=INDEX('T. S2 microarray results'!J:J, MATCH(TRUE, ('T. S2 microarray results'!B:B=B5) + ('T. S2 microarray results'!C:C=B5) + ('T. S2 microarray results'!D:D=B5) + ('T. S2 microarray results'!E:E=B5) + ('T. S2 microarray results'!F:F=B5) + ('T. S2 microarray results'!G:G=B5) + ('T. S2 microarray results'!H:H=B5) > 0, 0))} -> 0.1897815 | G5: {=INDEX('T. S2 microarray results'!K:K, MATCH(TRUE, ('T. S2 microarray results'!B:B=B5) + ('T. S2 microarray results'!C:C=B5) + ('T. S2 microarray results'!D:D=B5) + ('T. S2 microarray results'!E:E=B5) + ('T. S2 microarray results'!F:F=B5) + ('T. S2 microarray results'!G:G=B5) + ('T. S2 microarray results'!H:H=B5) > 0, 0))} -> 0.1657417 | H5: {=INDEX('T. S2 microarray results'!L:L, MATCH(TRUE, ('T. S2 microarray results'!B:B=B5) + ('T. S2 microarray results'!C:C=B5) + ('T. S2 microarray results'!D:D=B5) + ('T. S2 microarray results'!E:E=B5) + ('T. S2 microarray results'!F:F=B5) + ('T. S2 microarray results'!G:G=B5) + ('T. S2 microarray results'!H:H=B5) > 0, 0))} -> 0.1301702
A6: {=INDEX('T. S2 microarray results'!A:A, MATCH(TRUE, ('T. S2 microarray results'!B:B=B6) + ('T. S2 microarray results'!C:C=B6) + ('T. S2 microarray results'!D:D=B6) + ('T. S2 microarray results'!E:E=B6) + ('T. S2 microarray results'!F:F=B6) + ('T. S2 microarray results'!G:G=B6) + ('T. S2 microarray results'!H:H=B6) > 0, 0))} -> YNL148C | B6: ALF1 | C6: Candidate Gene | D6: =CONCATENATE(IF(C6="Known Longivity Gene","*",""),A6,"/",B6) -> YNL148C/ALF1 | E6: =IF(C6="Known Longivity Gene",1,0) -> 0 | F6: {=INDEX('T. S2 microarray results'!J:J, MATCH(TRUE, ('T. S2 microarray results'!B:B=B6) + ('T. S2 microarray results'!C:C=B6) + ('T. S2 microarray results'!D:D=B6) + ('T. S2 microarray results'!E:E=B6) + ('T. S2 microarray results'!F:F=B6) + ('T. S2 microarray results'!G:G=B6) + ('T. S2 microarray results'!H:H=B6) > 0, 0))} -> 0.3507553 | G6: {=INDEX('T. S2 microarray results'!K:K, MATCH(TRUE, ('T. S2 microarray results'!B:B=B6) + ('T. S2 microarray results'!C:C=B6) + ('T. S2 microarray results'!D:D=B6) + ('T. S2 microarray results'!E:E=B6) + ('T. S2 microarray results'!F:F=B6) + ('T. S2 microarray results'!G:G=B6) + ('T. S2 microarray results'!H:H=B6) > 0, 0))} -> 0.2453944 | H6: {=INDEX('T. S2 microarray results'!L:L, MATCH(TRUE, ('T. S2 microarray results'!B:B=B6) + ('T. S2 microarray results'!C:C=B6) + ('T. S2 microarray results'!D:D=B6) + ('T. S2 microarray results'!E:E=B6) + ('T. S2 microarray results'!F:F=B6) + ('T. S2 microarray results'!G:G=B6) + ('T. S2 microarray results'!H:H=B6) > 0, 0))} -> 0.3308809
A7: {=INDEX('T. S2 microarray results'!A:A, MATCH(TRUE, ('T. S2 microarray results'!B:B=B7) + ('T. S2 microarray results'!C:C=B7) + ('T. S2 microarray results'!D:D=B7) + ('T. S2 microarray results'!E:E=B7) + ('T. S2 microarray results'!F:F=B7) + ('T. S2 microarray results'!G:G=B7) + ('T. S2 microarray results'!H:H=B7) > 0, 0))} -> YPL120W | B7: VPS30 | C7: Candidate Gene | D7: =CONCATENATE(IF(C7="Known Longivity Gene","*",""),A7,"/",B7) -> YPL120W/VPS30 | E7: =IF(C7="Known Longivity Gene",1,0) -> 0 | F7: {=INDEX('T. S2 microarray results'!J:J, MATCH(TRUE, ('T. S2 microarray results'!B:B=B7) + ('T. S2 microarray results'!C:C=B7) + ('T. S2 microarray results'!D:D=B7) + ('T. S2 microarray results'!E:E=B7) + ('T. S2 microarray results'!F:F=B7) + ('T. S2 microarray results'!G:G=B7) + ('T. S2 microarray results'!H:H=B7) > 0, 0))} -> 0.2700111 | G7: {=INDEX('T. S2 microarray results'!K:K, MATCH(TRUE, ('T. S2 microarray results'!B:B=B7) + ('T. S2 microarray results'!C:C=B7) + ('T. S2 microarray results'!D:D=B7) + ('T. S2 microarray results'!E:E=B7) + ('T. S2 microarray results'!F:F=B7) + ('T. S2 microarray results'!G:G=B7) + ('T. S2 microarray results'!H:H=B7) > 0, 0))} -> 0.1998218 | H7: {=INDEX('T. S2 microarray results'!L:L, MATCH(TRUE, ('T. S2 microarray results'!B:B=B7) + ('T. S2 microarray results'!C:C=B7) + ('T. S2 microarray results'!D:D=B7) + ('T. S2 microarray results'!E:E=B7) + ('T. S2 microarray results'!F:F=B7) + ('T. S2 microarray results'!G:G=B7) + ('T. S2 microarray results'!H:H=B7) > 0, 0))} -> 0.3487854
A8: {=INDEX('T. S2 microarray results'!A:A, MATCH(TRUE, ('T. S2 microarray results'!B:B=B8) + ('T. S2 microarray results'!C:C=B8) + ('T. S2 microarray results'!D:D=B8) + ('T. S2 microarray results'!E:E=B8) + ('T. S2 microarray results'!F:F=B8) + ('T. S2 microarray results'!G:G=B8) + ('T. S2 microarray results'!H:H=B8) > 0, 0))} -> YLR268W | B8: SEC22 | C8: Candidate Gene | D8: =CONCATENATE(IF(C8="Known Longivity Gene","*",""),A8,"/",B8) -> YLR268W/SEC22 | E8: =IF(C8="Known Longivity Gene",1,0) -> 0 | F8: {=INDEX('T. S2 microarray results'!J:J, MATCH(TRUE, ('T. S2 microarray results'!B:B=B8) + ('T. S2 microarray results'!C:C=B8) + ('T. S2 microarray results'!D:D=B8) + ('T. S2 microarray results'!E:E=B8) + ('T. S2 microarray results'!F:F=B8) + ('T. S2 microarray results'!G:G=B8) + ('T. S2 microarray results'!H:H=B8) > 0, 0))} -> 0.5011193 | G8: {=INDEX('T. S2 microarray results'!K:K, MATCH(TRUE, ('T. S2 microarray results'!B:B=B8) + ('T. S2 microarray results'!C:C=B8) + ('T. S2 microarray results'!D:D=B8) + ('T. S2 microarray results'!E:E=B8) + ('T. S2 microarray results'!F:F=B8) + ('T. S2 microarray results'!G:G=B8) + ('T. S2 microarray results'!H:H=B8) > 0, 0))} -> 0.6050925 | H8: {=INDEX('T. S2 microarray results'!L:L, MATCH(TRUE, ('T. S2 microarray results'!B:B=B8) + ('T. S2 microarray results'!C:C=B8) + ('T. S2 microarray results'!D:D=B8) + ('T. S2 microarray results'!E:E=B8) + ('T. S2 microarray results'!F:F=B8) + ('T. S2 microarray results'!G:G=B8) + ('T. S2 microarray results'!H:H=B8) > 0, 0))} -> 0.5622788
A9: {=INDEX('T. S2 microarray results'!A:A, MATCH(TRUE, ('T. S2 microarray results'!B:B=B9) + ('T. S2 microarray results'!C:C=B9) + ('T. S2 microarray results'!D:D=B9) + ('T. S2 microarray results'!E:E=B9) + ('T. S2 microarray results'!F:F=B9) + ('T. S2 microarray results'!G:G=B9) + ('T. S2 microarray results'!H:H=B9) > 0, 0))} -> YKL015W | B9: PUT3 | C9: Candidate Gene | D9: =CONCATENATE(IF(C9="Known Longivity Gene","*",""),A9,"/",B9) -> YKL015W/PUT3 | E9: =IF(C9="Known Longivity Gene",1,0) -> 0 | F9: {=INDEX('T. S2 microarray results'!J:J, MATCH(TRUE, ('T. S2 microarray results'!B:B=B9) + ('T. S2 microarray results'!C:C=B9) + ('T. S2 microarray results'!D:D=B9) + ('T. S2 microarray results'!E:E=B9) + ('T. S2 microarray results'!F:F=B9) + ('T. S2 microarray results'!G:G=B9) + ('T. S2 microarray results'!H:H=B9) > 0, 0))} -> 0.0173433 | G9: {=INDEX('T. S2 microarray results'!K:K, MATCH(TRUE, ('T. S2 microarray results'!B:B=B9) + ('T. S2 microarray results'!C:C=B9) + ('T. S2 microarray results'!D:D=B9) + ('T. S2 microarray results'!E:E=B9) + ('T. S2 microarray results'!F:F=B9) + ('T. S2 microarray results'!G:G=B9) + ('T. S2 microarray results'!H:H=B9) > 0, 0))} -> -0.6754868 | H9: {=INDEX('T. S2 microarray results'!L:L, MATCH(TRUE, ('T. S2 microarray results'!B:B=B9) + ('T. S2 microarray results'!C:C=B9) + ('T. S2 microarray results'!D:D=B9) + ('T. S2 microarray results'!E:E=B9) + ('T. S2 microarray results'!F:F=B9) + ('T. S2 microarray results'!G:G=B9) + ('T. S2 microarray results'!H:H=B9) > 0, 0))} -> -0.7210857
A10: {=INDEX('T. S2 microarray results'!A:A, MATCH(TRUE, ('T. S2 microarray results'!B:B=B10) + ('T. S2 microarray results'!C:C=B10) + ('T. S2 microarray results'!D:D=B10) + ('T. S2 microarray results'!E:E=B10) + ('T. S2 microarray results'!F:F=B10) + ('T. S2 microarray results'!G:G=B10) + ('T. S2 microarray results'!H:H=B10) > 0, 0))} -> YCL037C | B10: SRO9 | C10: Candidate Gene | D10: =CONCATENATE(IF(C10="Known Longivity Gene","*",""),A10,"/",B10) -> YCL037C/SRO9 | E10: =IF(C10="Known Longivity Gene",1,0) -> 0 | F10: {=INDEX('T. S2 microarray results'!J:J, MATCH(TRUE, ('T. S2 microarray results'!B:B=B10) + ('T. S2 microarray results'!C:C=B10) + ('T. S2 microarray results'!D:D=B10) + ('T. S2 microarray results'!E:E=B10) + ('T. S2 microarray results'!F:F=B10) + ('T. S2 microarray results'!G:G=B10) + ('T. S2 microarray results'!H:H=B10) > 0, 0))} -> 0.01512819 | G10: {=INDEX('T. S2 microarray results'!K:K, MATCH(TRUE, ('T. S2 microarray results'!B:B=B10) + ('T. S2 microarray results'!C:C=B10) + ('T. S2 microarray results'!D:D=B10) + ('T. S2 microarray results'!E:E=B10) + ('T. S2 microarray results'!F:F=B10) + ('T. S2 microarray results'!G:G=B10) + ('T. S2 microarray results'!H:H=B10) > 0, 0))} -> 0.9660928 | H10: {=INDEX('T. S2 microarray results'!L:L, MATCH(TRUE, ('T. S2 microarray results'!B:B=B10) + ('T. S2 microarray results'!C:C=B10) + ('T. S2 microarray results'!D:D=B10) + ('T. S2 microarray results'!E:E=B10) + ('T. S2 microarray results'!F:F=B10) + ('T. S2 microarray results'!G:G=B10) + ('T. S2 microarray results'!H:H=B10) > 0, 0))} -> 0.07661917
A11: {=INDEX('T. S2 microarray results'!A:A, MATCH(TRUE, ('T. S2 microarray results'!B:B=B11) + ('T. S2 microarray results'!C:C=B11) + ('T. S2 microarray results'!D:D=B11) + ('T. S2 microarray results'!E:E=B11) + ('T. S2 microarray results'!F:F=B11) + ('T. S2 microarray results'!G:G=B11) + ('T. S2 microarray results'!H:H=B11) > 0, 0))} -> YKR026C | B11: GCN3 | C11: Candidate Gene | D11: =CONCATENATE(IF(C11="Known Longivity Gene","*",""),A11,"/",B11) -> YKR026C/GCN3 | E11: =IF(C11="Known Longivity Gene",1,0) -> 0 | F11: {=INDEX('T. S2 microarray results'!J:J, MATCH(TRUE, ('T. S2 microarray results'!B:B=B11) + ('T. S2 microarray results'!C:C=B11) + ('T. S2 microarray results'!D:D=B11) + ('T. S2 microarray results'!E:E=B11) + ('T. S2 microarray results'!F:F=B11) + ('T. S2 microarray results'!G:G=B11) + ('T. S2 microarray results'!H:H=B11) > 0, 0))} -> 0.09773856 | G11: {=INDEX('T. S2 microarray results'!K:K, MATCH(TRUE, ('T. S2 microarray results'!B:B=B11) + ('T. S2 microarray results'!C:C=B11) + ('T. S2 microarray results'!D:D=B11) + ('T. S2 microarray results'!E:E=B11) + ('T. S2 microarray results'!F:F=B11) + ('T. S2 microarray results'!G:G=B11) + ('T. S2 microarray results'!H:H=B11) > 0, 0))} -> 0.5938986 | H11: {=INDEX('T. S2 microarray results'!L:L, MATCH(TRUE, ('T. S2 microarray results'!B:B=B11) + ('T. S2 microarray results'!C:C=B11) + ('T. S2 microarray results'!D:D=B11) + ('T. S2 microarray results'!E:E=B11) + ('T. S2 microarray results'!F:F=B11) + ('T. S2 microarray results'!G:G=B11) + ('T. S2 microarray results'!H:H=B11) > 0, 0))} -> 0.0981128
A12: {=INDEX('T. S2 microarray results'!A:A, MATCH(TRUE, ('T. S2 microarray results'!B:B=B12) + ('T. S2 microarray results'!C:C=B12) + ('T. S2 microarray results'!D:D=B12) + ('T. S2 microarray results'!E:E=B12) + ('T. S2 microarray results'!F:F=B12) + ('T. S2 microarray results'!G:G=B12) + ('T. S2 microarray results'!H:H=B12) > 0, 0))} -> YKL017C | B12: HCS1 | C12: Candidate Gene | D12: =CONCATENATE(IF(C12="Known Longivity Gene","*",""),A12,"/",B12) -> YKL017C/HCS1 | E12: =IF(C12="Known Longivity Gene",1,0) -> 0 | F12: {=INDEX('T. S2 microarray results'!J:J, MATCH(TRUE, ('T. S2 microarray results'!B:B=B12) + ('T. S2 microarray results'!C:C=B12) + ('T. S2 microarray results'!D:D=B12) + ('T. S2 microarray results'!E:E=B12) + ('T. S2 microarray results'!F:F=B12) + ('T. S2 microarray results'!G:G=B12) + ('T. S2 microarray results'!H:H=B12) > 0, 0))} -> 0.1866696 | G12: {=INDEX('T. S2 microarray results'!K:K, MATCH(TRUE, ('T. S2 microarray results'!B:B=B12) + ('T. S2 microarray results'!C:C=B12) + ('T. S2 microarray results'!D:D=B12) + ('T. S2 microarray results'!E:E=B12) + ('T. S2 microarray results'!F:F=B12) + ('T. S2 microarray results'!G:G=B12) + ('T. S2 microarray results'!H:H=B12) > 0, 0))} -> -0.3403223 | H12: {=INDEX('T. S2 microarray results'!L:L, MATCH(TRUE, ('T. S2 microarray results'!B:B=B12) + ('T. S2 microarray results'!C:C=B12) + ('T. S2 microarray results'!D:D=B12) + ('T. S2 microarray results'!E:E=B12) + ('T. S2 microarray results'!F:F=B12) + ('T. S2 microarray results'!G:G=B12) + ('T. S2 microarray results'!H:H=B12) > 0, 0))} -> 0.005202552
A13: {=INDEX('T. S2 microarray results'!A:A, MATCH(TRUE, ('T. S2 microarray results'!B:B=B13) + ('T. S2 microarray results'!C:C=B13) + ('T. S2 microarray results'!D:D=B13) + ('T. S2 microarray results'!E:E=B13) + ('T. S2 microarray results'!F:F=B13) + ('T. S2 microarray results'!G:G=B13) + ('T. S2 microarray results'!H:H=B13) > 0, 0))} -> YCR002C | B13: CDC10 | C13: Candidate Gene | D13: =CONCATENATE(IF(C13="Known Longivity Gene","*",""),A13,"/",B13) -> YCR002C/CDC10 | E13: =IF(C13="Known Longivity Gene",1,0) -> 0 | F13: {=INDEX('T. S2 microarray results'!J:J, MATCH(TRUE, ('T. S2 microarray results'!B:B=B13) + ('T. S2 microarray results'!C:C=B13) + ('T. S2 microarray results'!D:D=B13) + ('T. S2 microarray results'!E:E=B13) + ('T. S2 microarray results'!F:F=B13) + ('T. S2 microarray results'!G:G=B13) + ('T. S2 microarray results'!H:H=B13) > 0, 0))} -> -0.2811855 | G13: {=INDEX('T. S2 microarray results'!K:K, MATCH(TRUE, ('T. S2 microarray results'!B:B=B13) + ('T. S2 microarray results'!C:C=B13) + ('T. S2 microarray results'!D:D=B13) + ('T. S2 microarray results'!E:E=B13) + ('T. S2 microarray results'!F:F=B13) + ('T. S2 microarray results'!G:G=B13) + ('T. S2 microarray results'!H:H=B13) > 0, 0))} -> -0.4761917 | H13: {=INDEX('T. S2 microarray results'!L:L, MATCH(TRUE, ('T. S2 microarray results'!B:B=B13) + ('T. S2 microarray results'!C:C=B13) + ('T. S2 microarray results'!D:D=B13) + ('T. S2 microarray results'!E:E=B13) + ('T. S2 microarray results'!F:F=B13) + ('T. S2 microarray results'!G:G=B13) + ('T. S2 microarray results'!H:H=B13) > 0, 0))} -> -0.03376408
... A171: {=INDEX('T. S2 microarray results'!A:A, MATCH(TRUE, ('T. S2 microarray results'!B:B=B171) + ('T. S2 microarray results'!C:C=B171) + ('T. S2 microarray results'!D:D=B171) + ('T. S2 microarray results'!E:E=B171) + ('T. S2 microarray results'!F:F=B171) + ('T. S2 microarray results'!G:G=B171) + ('T. S2 microarray results'!H:H=B171) > 0, 0))} -> YMR273C | B171: ZDS1 | C171: Known Longivity Gene | D171: =CONCATENATE(IF(C171="Known Longivity Gene","*",""),A171,"/",B171) -> *YMR273C/ZDS1 | E171: =IF(C171="Known Longivity Gene",1,0) -> 1 | F171: {=INDEX('T. S2 microarray results'!J:J, MATCH(TRUE, ('T. S2 microarray results'!B:B=B171) + ('T. S2 microarray results'!C:C=B171) + ('T. S2 microarray results'!D:D=B171) + ('T. S2 microarray results'!E:E=B171) + ('T. S2 microarray results'!F:F=B171) + ('T. S2 microarray results'!G:G=B171) + ('T. S2 microarray results'!H:H=B171) > 0, 0))} -> -0.5049685 | G171: {=INDEX('T. S2 microarray results'!K:K, MATCH(TRUE, ('T. S2 microarray results'!B:B=B171) + ('T. S2 microarray results'!C:C=B171) + ('T. S2 microarray results'!D:D=B171) + ('T. S2 microarray results'!E:E=B171) + ('T. S2 microarray results'!F:F=B171) + ('T. S2 microarray results'!G:G=B171) + ('T. S2 microarray results'!H:H=B171) > 0, 0))} -> -0.9081731 | H171: {=INDEX('T. S2 microarray results'!L:L, MATCH(TRUE, ('T. S2 microarray results'!B:B=B171) + ('T. S2 microarray results'!C:C=B171) + ('T. S2 microarray results'!D:D=B171) + ('T. S2 microarray results'!E:E=B171) + ('T. S2 microarray results'!F:F=B171) + ('T. S2 microarray results'!G:G=B171) + ('T. S2 microarray results'!H:H=B171) > 0, 0))} -> -0.4852084
